LICENSE.md
MANIFEST.in
README.md
setup.py
bootstrap4/__init__.py
bootstrap4.egg-info/PKG-INFO
bootstrap4.egg-info/SOURCES.txt
bootstrap4.egg-info/dependency_links.txt
bootstrap4.egg-info/top_level.txt
bootstrap4/statics/css/bootstrap-grid.css
bootstrap4/statics/css/bootstrap-grid.css.map
bootstrap4/statics/css/bootstrap-grid.min.css
bootstrap4/statics/css/bootstrap-grid.min.css.map
bootstrap4/statics/css/bootstrap-reboot.css
bootstrap4/statics/css/bootstrap-reboot.css.map
bootstrap4/statics/css/bootstrap-reboot.min.css
bootstrap4/statics/css/bootstrap-reboot.min.css.map
bootstrap4/statics/css/bootstrap.css
bootstrap4/statics/css/bootstrap.css.map
bootstrap4/statics/css/bootstrap.min.css
bootstrap4/statics/css/bootstrap.min.css.map
bootstrap4/statics/js/bootstrap.bundle.js
bootstrap4/statics/js/bootstrap.bundle.js.map
bootstrap4/statics/js/bootstrap.bundle.min.js
bootstrap4/statics/js/bootstrap.bundle.min.js.map
bootstrap4/statics/js/bootstrap.js
bootstrap4/statics/js/bootstrap.js.map
bootstrap4/statics/js/bootstrap.min.js
bootstrap4/statics/js/bootstrap.min.js.map
bootstrap4/templates/form.html
bootstrap4/templates/inputs/checkbox.html
bootstrap4/templates/inputs/input.html
bootstrap4/templates/inputs/select.html
bootstrap4/templates/inputs/textarea.html